struct_logs/__init__.py
struct_logs/configure.py
harken_struct_logs-0.1.0.dist-info/METADATA
harken_struct_logs-0.1.0.dist-info/WHEEL
harken_struct_logs-0.1.0.dist-info/RECORD
