Metadata-Version: 2.1
Name: harken-struct_logs
Version: 0.1.0
Summary: ...
Author: Juan Luis García
Author-email: juanluis1702@gmail.com
Requires-Python: >=3.10
Classifier: Programming Language :: Python :: 3
Classifier: Programming Language :: Python :: 3.10
Classifier: Programming Language :: Python :: 3.11
Classifier: Programming Language :: Python :: 3.12
Requires-Dist: funcy (==2.0.0)
Requires-Dist: poetry (==1.7.1)
Requires-Dist: structlog (==23.1.0)
